ldap_ui/__init__.py
ldap_ui/__main__.py
ldap_ui/app.py
ldap_ui/entities.py
ldap_ui/ldap_api.py
ldap_ui/ldap_helpers.py
ldap_ui/schema.py
ldap_ui/settings.py
ldap_ui/statics/favicon.ico
ldap_ui/statics/index.html
ldap_ui/statics/assets/fontawesome-webfont-B-jkhYfk.woff2
ldap_ui/statics/assets/fontawesome-webfont-CDK5bt4p.woff
ldap_ui/statics/assets/fontawesome-webfont-CQDK8MU3.ttf
ldap_ui/statics/assets/fontawesome-webfont-D13rzr4g.svg
ldap_ui/statics/assets/fontawesome-webfont-G5YE5S7X.eot
ldap_ui/statics/assets/index-CLhimpsr.js
ldap_ui/statics/assets/index-CLhimpsr.js.gz
ldap_ui/statics/assets/index-Zs8eqVyc.css
ldap_ui/statics/assets/index-Zs8eqVyc.css.gz
ldap_ui-0.11.0.dist-info/licenses/LICENSE.txt
ldap_ui-0.11.0.dist-info/METADATA
ldap_ui-0.11.0.dist-info/WHEEL
ldap_ui-0.11.0.dist-info/entry_points.txt
ldap_ui-0.11.0.dist-info/top_level.txt
ldap_ui-0.11.0.dist-info/RECORD
