Metadata-Version: 2.4
Name: ldap-ui
Version: 0.11.0
Summary: A fast and versatile LDAP editor
Author: dnknth
License-Expression: MIT
Project-URL: Repository, https://github.com/dnknth/ldap-ui
Keywords: ldap,web-ui,python3
Classifier: Operating System :: OS Independent
Classifier: Development Status :: 4 - Beta
Classifier: Intended Audience :: Developers
Classifier: Programming Language :: Python :: 3 :: Only
Classifier: Topic :: Software Development :: Libraries
Requires-Python: >=3.10
License-File: LICENSE.txt
Requires-Dist: fastapi>=0.115.12
Requires-Dist: python-ldap
Requires-Dist: python-multipart
Requires-Dist: uvicorn>=0.34.3
Dynamic: license-file
